niti_vajra_plugin/__init__.py
niti_vajra_plugin/plugin.py
niti_vajra_plugin/rules/__init__.py
niti_vajra_plugin/rules/forward_declaration_rule.py
niti_vajra_plugin/rules/pch_rule.py
niti_vajra_plugin-1.0.0.dist-info/licenses/LICENSE
niti_vajra_plugin-1.0.0.dist-info/METADATA
niti_vajra_plugin-1.0.0.dist-info/WHEEL
niti_vajra_plugin-1.0.0.dist-info/entry_points.txt
niti_vajra_plugin-1.0.0.dist-info/top_level.txt
niti_vajra_plugin-1.0.0.dist-info/RECORD
