Metadata-Version: 2.4
Name: niti-vajra-plugin
Version: 1.0.0
Summary: Vajra-specific linting rules for C++ projects for Niti linter
License: Apache 2.0
Project-URL: Repository, https://github.com/project-vajra/niti-vajra-plugin.git
Project-URL: Documentation, https://project-vajra.github.io/niti/
Project-URL: Bug Tracker, https://github.com/project-vajra/niti-vajra-plugin/issues
Keywords: c++,linter,static-analysis,code-quality
Classifier: Development Status :: 4 - Beta
Classifier: Intended Audience :: Developers
Classifier: Programming Language :: Python :: 3
Classifier: Programming Language :: Python :: 3.8
Classifier: Programming Language :: Python :: 3.9
Classifier: Programming Language :: Python :: 3.10
Classifier: Programming Language :: Python :: 3.11
Requires-Python: >=3.8
License-File: LICENSE
Requires-Dist: niti>=0.1.0
Dynamic: license-file
